eulerian_marketing_platform/__init__.py
eulerian_marketing_platform/server.py
eulerian_marketing_platform-0.2.8.dist-info/LICENSE
eulerian_marketing_platform-0.2.8.dist-info/METADATA
eulerian_marketing_platform-0.2.8.dist-info/WHEEL
eulerian_marketing_platform-0.2.8.dist-info/entry_points.txt
eulerian_marketing_platform-0.2.8.dist-info/top_level.txt
eulerian_marketing_platform-0.2.8.dist-info/RECORD
