Metadata-Version: 2.1
Name: eulerian-marketing-platform
Version: 0.2.8
Summary: MCP server for Eulerian Marketing Platform - enables AI assistants to interact with Eulerian's marketing analytics and campaign management APIs
Author-email: Eulerian Technologies <mathieu@eulerian.com>
License: MIT
Project-URL: Homepage, https://github.com/EulerianTechnologies/eulerian-marketing-platform-mcp
Project-URL: Issues, https://github.com/EulerianTechnologies/eulerian-marketing-platform-mcp/issues
Project-URL: Documentation, https://github.com/EulerianTechnologies/eulerian-marketing-platform-mcp#readme
Project-URL: Repository, https://github.com/EulerianTechnologies/eulerian-marketing-platform-mcp
Classifier: Development Status :: 4 - Beta
Classifier: Intended Audience :: Developers
Classifier: License :: OSI Approved :: MIT License
Classifier: Operating System :: OS Independent
Classifier: Operating System :: Microsoft :: Windows
Classifier: Operating System :: POSIX :: Linux
Classifier: Operating System :: MacOS
Classifier: Programming Language :: Python :: 3
Classifier: Programming Language :: Python :: 3.10
Classifier: Programming Language :: Python :: 3.11
Classifier: Programming Language :: Python :: 3.12
Classifier: Topic :: Software Development :: Libraries :: Python Modules
Requires-Python: >=3.10
License-File: LICENSE
Requires-Dist: httpx (>=0.25.0)
Provides-Extra: deployment
Requires-Dist: uv (>=0.5.0) ; extra == 'deployment'
Provides-Extra: dev
Requires-Dist: black (>=23.0.0) ; extra == 'dev'
Requires-Dist: mypy (>=1.0.0) ; extra == 'dev'
Requires-Dist: pytest-asyncio (>=0.21.0) ; extra == 'dev'
Requires-Dist: pytest-cov (>=4.0.0) ; extra == 'dev'
Requires-Dist: pytest (>=7.0.0) ; extra == 'dev'
Requires-Dist: ruff (>=0.1.0) ; extra == 'dev'
